fiona_settings/__init__.py
fiona_settings/__version__.py
fiona_settings/models.py
test/__init__.py
test/test_settings.py
fiona_settings-0.1.0.dist-info/LICENSE
fiona_settings-0.1.0.dist-info/METADATA
fiona_settings-0.1.0.dist-info/WHEEL
fiona_settings-0.1.0.dist-info/top_level.txt
fiona_settings-0.1.0.dist-info/RECORD
