Metadata-Version: 2.1
Name: fiona_settings
Version: 0.1.0
Summary: Wrappers for fiona settings.
Home-page: https://github.com/tomplex/fiona_settings
Author: Tom Caruso
Author-email: carusot42@gmail.com
License: MIT
Platform: UNKNOWN
Classifier: License :: OSI Approved :: MIT License
Classifier: Programming Language :: Python
Classifier: Programming Language :: Python :: 3
Classifier: Programming Language :: Python :: 3.6
Classifier: Programming Language :: Python :: Implementation :: CPython
Requires-Python: >=3.6.0
